aspect/__init__.py
aspect/action.py
aspect/actionListener.py
aspect/actionTest.py
aspect/report.py
aop_on_robot-0.0.2.dist-info/LICENSE
aop_on_robot-0.0.2.dist-info/METADATA
aop_on_robot-0.0.2.dist-info/WHEEL
aop_on_robot-0.0.2.dist-info/top_level.txt
aop_on_robot-0.0.2.dist-info/RECORD
