Metadata-Version: 2.1
Name: aop-on-robot
Version: 0.0.2
Summary: UNKNOWN
Home-page: https://ssl-gitlab.csie.ntut.edu.tw/e8315402/aop-on-robot
Author: Software System Laboratory
Author-email: ntutsoftsyslab@gmail.com
License: UNKNOWN
Platform: UNKNOWN
Classifier: Programming Language :: Python :: 3.6
Classifier: Framework :: Robot Framework
Classifier: Topic :: Software Development :: Testing :: Acceptance
Requires-Python: >=3.6
